marathi_jokes/__init__.py
marathi_jokes/jokes.py
marathi_jokes-0.1.1.dist-info/licenses/LICENSE
marathi_jokes-0.1.1.dist-info/METADATA
marathi_jokes-0.1.1.dist-info/WHEEL
marathi_jokes-0.1.1.dist-info/top_level.txt
marathi_jokes-0.1.1.dist-info/RECORD
