Metadata-Version: 2.4
Name: marathi-jokes
Version: 0.1.1
Summary: A fun Marathi Jokes library 😂
Home-page: https://github.com/yourusername/marathi-jokes
Author: Aditya Pawar
Author-email: your_email@example.com
Classifier: Programming Language :: Python :: 3
Classifier: Operating System :: OS Independent
Requires-Python: >=3.6
License-File: LICENSE
Dynamic: author
Dynamic: author-email
Dynamic: classifier
Dynamic: description
Dynamic: description-content-type
Dynamic: home-page
Dynamic: license-file
Dynamic: requires-python
Dynamic: summary
